spotify_extractor/__init__.py
spotify_extractor/cli.py
spotify_extractor/core.py
spotify_extractor/helpers.py
spotify_playlist_extractor-1.0.1.dist-info/licenses/LICENSE
spotify_playlist_extractor-1.0.1.dist-info/METADATA
spotify_playlist_extractor-1.0.1.dist-info/WHEEL
spotify_playlist_extractor-1.0.1.dist-info/entry_points.txt
spotify_playlist_extractor-1.0.1.dist-info/top_level.txt
spotify_playlist_extractor-1.0.1.dist-info/RECORD
