Metadata-Version: 2.4
Name: spotify-playlist-extractor
Version: 1.0.1
Summary: استخراج ساده و سریع پلی‌لیست‌های اسپاتیفای
Home-page: https://github.com/MohammadHNdev/Spotify-Playlist-Extractor
Author: Mohammad Hossein Norouzi
Author-email: mohammadhn.dev@gmail.com
Project-URL: Bug Reports, https://github.com/MohammadHNdev/Spotify-Playlist-Extractor/issues
Project-URL: Source, https://github.com/MohammadHNdev/Spotify-Playlist-Extractor
Project-URL: Documentation, https://github.com/MohammadHNdev/Spotify-Playlist-Extractor#readme
Keywords: spotify playlist music extractor download links
Classifier: Development Status :: 5 - Production/Stable
Classifier: Intended Audience :: Developers
Classifier: License :: OSI Approved :: MIT License
Classifier: Operating System :: OS Independent
Classifier: Programming Language :: Python :: 3
Classifier: Programming Language :: Python :: 3.8
Classifier: Programming Language :: Python :: 3.9
Classifier: Programming Language :: Python :: 3.10
Classifier: Programming Language :: Python :: 3.11
Classifier: Programming Language :: Python :: 3.12
Classifier: Topic :: Software Development :: Libraries :: Python Modules
Classifier: Topic :: Multimedia :: Sound/Audio
Classifier: Topic :: Internet :: WWW/HTTP :: Dynamic Content
Requires-Python: >=3.8
License-File: LICENSE
Requires-Dist: spotipy>=2.22.1
Requires-Dist: requests>=2.28.0
Requires-Dist: python-dotenv>=0.19.0
Provides-Extra: web
Requires-Dist: streamlit>=1.20.0; extra == "web"
Requires-Dist: pandas>=1.3.0; extra == "web"
Provides-Extra: dev
Requires-Dist: pytest>=7.0.0; extra == "dev"
Requires-Dist: black>=22.0.0; extra == "dev"
Requires-Dist: flake8>=4.0.0; extra == "dev"
Dynamic: author
Dynamic: author-email
Dynamic: classifier
Dynamic: description
Dynamic: description-content-type
Dynamic: home-page
Dynamic: keywords
Dynamic: license-file
Dynamic: project-url
Dynamic: provides-extra
Dynamic: requires-dist
Dynamic: requires-python
Dynamic: summary
